README.md
setup.py
probability_distributions_101/Binomialdistribution.py
probability_distributions_101/Gaussiandistribution.py
probability_distributions_101/Generaldistribution.py
probability_distributions_101/__init__.py
probability_distributions_101.egg-info/PKG-INFO
probability_distributions_101.egg-info/SOURCES.txt
probability_distributions_101.egg-info/dependency_links.txt
probability_distributions_101.egg-info/not-zip-safe
probability_distributions_101.egg-info/top_level.txt