Metadata-Version: 1.0
Name: probability-distributions-101
Version: 0.2
Summary: Gaussian and Binomial distributions
Home-page: UNKNOWN
Author: Wided Ahlem Touhami
Author-email: w.touhami@esi-sba.dz
License: UNKNOWN
Platform: UNKNOWN
